setup.py
microbitble/__init__.py
microbitble/smarthub.py
microbitble.egg-info/PKG-INFO
microbitble.egg-info/SOURCES.txt
microbitble.egg-info/dependency_links.txt
microbitble.egg-info/requires.txt
microbitble.egg-info/top_level.txt
microbitble/bluetooth/__init__.py
microbitble/input_output/__init__.py
microbitble/services/__init__.py
microbitble/utils/__init__.py
microbitble/utils/byte_utils.py